python_wikibase/__init__.py
python_wikibase/__version__.py
python_wikibase/base.py
python_wikibase/data_model/__init__.py
python_wikibase/data_model/alias.py
python_wikibase/data_model/claim.py
python_wikibase/data_model/description.py
python_wikibase/data_model/entity.py
python_wikibase/data_model/label.py
python_wikibase/data_model/qualifier.py
python_wikibase/data_model/reference.py
python_wikibase/data_types/__init__.py
python_wikibase/data_types/data_type.py
python_wikibase/data_types/external_id.py
python_wikibase/data_types/geo_location.py
python_wikibase/data_types/quantity.py
python_wikibase/data_types/string_value.py
python_wikibase/python_wikibase.py
python_wikibase/utils/__init__.py
python_wikibase/utils/data_types.py
python_wikibase/utils/exceptions.py
python_wikibase/value.py
python_wikibase-0.1.0.dist-info/LICENSE
python_wikibase-0.1.0.dist-info/LICENSE-APACHE-2.0
python_wikibase-0.1.0.dist-info/LICENSE-GPL-3.0
python_wikibase-0.1.0.dist-info/WHEEL
python_wikibase-0.1.0.dist-info/METADATA
python_wikibase-0.1.0.dist-info/RECORD
