Metadata-Version: 2.1
Name: python-wikibase
Version: 0.1.0
Summary: Wikibase queries and edits made easy
Home-page: https://github.com/samuelmeuli/python-wikibase
License: UNKNOWN
Keywords: wikibase,wikidata,bot,api,wrapper
Author: Samuel Meuli
Author-email: me@samuelmeuli.com
Requires-Python: >=3.6,<4.0
Classifier: Intended Audience :: Developers
Classifier: Programming Language :: Python :: 3
Classifier: Programming Language :: Python :: 3.6
Classifier: Programming Language :: Python :: 3.7
Classifier: Topic :: Internet
Classifier: Topic :: Internet :: WWW/HTTP :: Dynamic Content :: Wiki
Classifier: Topic :: Software Development :: Libraries :: Python Modules
Requires-Dist: wikibase-api (>=0.1.0,<0.2.0)
Project-URL: Documentation, https://github.com/samuelmeuli/python-wikibase/blob/master/docs/usage.md
Project-URL: Repository, https://github.com/samuelmeuli/python-wikibase
